{"name":"stubby4j","tagline":"HTTP stub server written in Java with embedded Jetty","body":"[![Build Status](https://secure.travis-ci.org/azagniotov/stubby4j.png?branch=master)](http://travis-ci.org/azagniotov/stubby4j)\r\n\r\n# stubby4j\r\n\r\nA stub HTTP server written in Java with embedded Jetty server\t\r\n##### Why the word \"stubby\"?\r\nIt is a stub HTTP server after all, hence the \"stubby\". Also, in Australian slang \"stubby\" means _beer bottle_\r\n\r\n## Why would a developer use stubby4j?\r\n####You want to:\r\n* Simulate responses from real server and don't care (or cannot) to go over the network\r\n* Verify that your code makes HTTP requests with all the required parameters and/or headers\r\n* Verify that your code correctly handles HTTP error codes\r\n* You want to trigger response from the server based on the request parameters over HTTP or HTTPS\r\n* Support for any of the available HTTP methods\r\n* Simulate support for Basic Authorization\r\n* Support for HTTP 30x redirects\r\n* Trigger multiple responses based on multiple requests on the same URI\r\n* Configure stub data using configuration file\r\n* Configure stub data at runtime, without restarting the server by making a POST to an exposed endpoint\r\n* Provide canned answers in your contract/integration tests\r\n* Enable delayed responses for performance and stability testing\r\n* Avoid to spend time coding for the above requirements\r\n* Concentrate on the task at hand\r\n\r\n\r\n\r\n## Why would a QA use stubby4j?\r\n* Specifiable mock responses to simulate page conditions without real data.\r\n* Easily swappable data config files to run different data sets and responses.\r\n* All-in-one stub server to handle mock data with less need to upkeep code for test generation\r\n\r\n###### All this goodness in just under 1.5MB\r\n\r\n## Dependencies\r\nstubby4j is a fat JAR (for the skinny JAR, please look under `artifacts`), which contains the following dependencies:\r\n\r\n* jetty-server-8.1.1.v20120215.jar\r\n* javax.servlet-3.0.0.v201112011016.jar\r\n* jetty-continuation-8.1.1.v20120215.jar\r\n* jetty-http-8.1.1.v20120215.jar\r\n* jetty-io-8.1.1.v20120215.jar\r\n* jetty-util-8.1.1.v20120215.jar\r\n* commons-cli-1.2.jar\r\n* commons-codec-1.5.jar\r\n* snakeyaml-1.11.jar\r\n\r\n**stubby4j is also compatible with Jetty 7.x.x and servlet API v2.5**\r\n\r\n\r\n## Documentation\r\nSee `docs` directory for:\r\n\r\n* [Build Instructions](https://github.com/azagniotov/stubby4j/blob/master/docs/BUILDING.md)\r\n* [Commandline Usage](https://github.com/azagniotov/stubby4j/blob/master/docs/COMMAND-LINE-USAGE.md)\r\n* [Code Examples](https://github.com/azagniotov/stubby4j/blob/master/docs/CODE-EXAMPLES.md)\r\n* [YAML Sample](https://github.com/azagniotov/stubby4j/blob/master/docs/YAML.md)\r\n\r\n\r\n## Artifacts\r\nSee `artifacts` directory for the following stubby4j JARs:\r\n* Fat\r\n* Skinny\r\n* Sources\r\n* Javadocs\r\n\r\n\r\n## Authors\r\nSee AUTHORS.md for details.\r\n\r\n\r\n## Kudos\r\nSee THANKS.md for details.\r\n\r\n\r\n## See Also\r\n**[stubby4node](https://github.com/Afmrak/stubby4node):** A NodeJS implementation of stubby4j\r\n\r\n\r\n## Copyright\r\nSee COPYRIGHT for details.","google":"","note":"Don't delete this file! It's used internally to help with page regeneration."}